credmgr/.credmgr.ini
credmgr/__init__.py
credmgr/auth.py
credmgr/config.py
credmgr/const.py
credmgr/credmgr.py
credmgr/deprecation_decorator.py
credmgr/exceptions.py
credmgr/requestor.py
credmgr/mixins/__init__.py
credmgr/mixins/base.py
credmgr/mixins/base_app.py
credmgr/mixins/deletable.py
credmgr/mixins/editable.py
credmgr/mixins/owner.py
credmgr/mixins/reddit_app.py
credmgr/models/__init__.py
credmgr/models/bot.py
credmgr/models/database_credential.py
credmgr/models/helpers.py
credmgr/models/reddit_app.py
credmgr/models/refresh_token.py
credmgr/models/schemas.py
credmgr/models/sentry_token.py
credmgr/models/user.py
credmgr/models/user_verification.py
credmgr/models/utils.py
credmgr-1.6.0.dist-info/LICENSE.txt
credmgr-1.6.0.dist-info/METADATA
credmgr-1.6.0.dist-info/WHEEL
credmgr-1.6.0.dist-info/top_level.txt
credmgr-1.6.0.dist-info/RECORD
